staticconf/__init__.py
staticconf/config.py
staticconf/errors.py
staticconf/getters.py
staticconf/loader.py
staticconf/proxy.py
staticconf/py.typed
staticconf/readers.py
staticconf/schema.py
staticconf/testing.py
staticconf/validation.py
staticconf/version.py
PyStaticConfiguration-0.11.1.dist-info/LICENSE
PyStaticConfiguration-0.11.1.dist-info/METADATA
PyStaticConfiguration-0.11.1.dist-info/WHEEL
PyStaticConfiguration-0.11.1.dist-info/top_level.txt
PyStaticConfiguration-0.11.1.dist-info/RECORD
